webbpsf_ext/__init__.py
webbpsf_ext/analysis_tools.py
webbpsf_ext/bandpasses.py
webbpsf_ext/conftest.py
webbpsf_ext/coords.py
webbpsf_ext/coron_masks.py
webbpsf_ext/image_manip.py
webbpsf_ext/imreg_tools.py
webbpsf_ext/logging_utils.py
webbpsf_ext/maths.py
webbpsf_ext/opds.py
webbpsf_ext/psfs.py
webbpsf_ext/robust.py
webbpsf_ext/spectra.py
webbpsf_ext/synphot_ext.py
webbpsf_ext/utils.py
webbpsf_ext/version.py
webbpsf_ext/webbpsf_ext_core.py
webbpsf_ext/wext_style.mplstyle
webbpsf_ext/spectral_data/zhu15_accr.txt
webbpsf_ext/spectral_data/bosz2024_grids/README
webbpsf_ext/spectral_data/bosz2024_grids/R2000/bosz2024_wave_r2000.txt
webbpsf_ext/spectral_data/bosz2024_grids/R500/bosz2024_wave_r500.txt
webbpsf_ext/spectral_data/bosz_grids/README
webbpsf_ext/spectral_data/bosz_grids/R200/bosz_wget_R200_fits.sh
webbpsf_ext/spectral_data/bosz_grids/R2000/bosz_wget_R2000_fits.sh
webbpsf_ext/spectral_data/bosz_grids/R20000/bosz_wget_R20000_fits.sh
webbpsf_ext/spectral_data/cond_models/FORMAT
webbpsf_ext/spectral_data/cond_models/README
webbpsf_ext/spectral_data/cond_models/README2
webbpsf_ext/spectral_data/cond_models/model.AMES-Cond-2000.M-0.0.JWST.Vega
webbpsf_ext/spectral_data/cond_models/model.AMES-Cond-2000.M-0.0.JWST.Vega.F200W.npy
webbpsf_ext/spectral_data/cond_models/model.AMES-Cond-2000.M-0.0.JWST.Vega.F210M.npy
webbpsf_ext/spectral_data/cond_models/model.AMES-Cond-2000.M-0.0.JWST.Vega.F410M.npy
webbpsf_ext/spectral_data/cond_models/model.AMES-Cond-2000.M-0.0.JWST.Vega.F444W.npy
webbpsf_ext/spectral_data/cond_models/model.AMES-Cond-2000.M-0.0.JWST.Vega.F480M.npy
webbpsf_ext/spectral_data/cond_models/model.AMES-dusty.M-0.0.JWST.Vega
webbpsf_ext/spectral_data/cond_models/model.BT-Dusty.M-0.0.JWST.Vega
webbpsf_ext/spectral_data/cond_models/model.BT-Dusty.M-0.5.JWST.Vega
webbpsf_ext/spectral_data/cond_models/model.BT-Dusty.M-1.0.JWST.Vega
webbpsf_ext/spectral_data/linder/linder2019.pdf
webbpsf_ext/spectral_data/linder/cooling_curves/BEX_evol_mags_-2_MH_-0.4_ME_005.dat
webbpsf_ext-2.0.1.dist-info/LICENSE
webbpsf_ext-2.0.1.dist-info/METADATA
webbpsf_ext-2.0.1.dist-info/WHEEL
webbpsf_ext-2.0.1.dist-info/top_level.txt
webbpsf_ext-2.0.1.dist-info/RECORD
