Metadata-Version: 2.1
Name: webbpsf-ext
Version: 2.0.1
Summary: WebbPSF Extensions
Home-page: https://github.com/JarronL/webbpsf_ext
Author: Jarron Leisenring
Author-email: jarronl@arizona.edu
License: MIT license
Keywords: jwst psf nircam miri simulation
Classifier: Development Status :: 5 - Production/Stable
Classifier: Intended Audience :: Developers
Classifier: Topic :: Scientific/Engineering :: Astronomy
Classifier: License :: OSI Approved :: MIT License
Classifier: Programming Language :: Python :: 3
Classifier: Programming Language :: Python :: 3.10
Classifier: Programming Language :: Python :: 3.11
License-File: LICENSE
Requires-Dist: matplotlib (>=3.7.1)
Requires-Dist: tqdm (>4)
Requires-Dist: scikit-image (>=0.20.0)
Requires-Dist: synphot (>=1.2.1)
Requires-Dist: poppy (>=1.1.0)
Requires-Dist: stpsf (>=2.0.0)
Requires-Dist: pysiaf (>=0.24.1)
Requires-Dist: stsynphot
